<?xml version="1.0" encoding="UTF-8"?>
<export version="E">
  <design>
    <source>/github/workspace/hw/sch_pcb/PROGLOG01.kicad_sch</source>
    <date>Wed Jul  5 00:38:25 2023</date>
    <tool>Eeschema 6.0.11+dfsg-1~bpo11+1</tool>
    <sheet number="1" name="/" tstamps="/">
      <title_block>
        <title>PROGLOG01B</title>
        <company>Mlab www.mlab.cz</company>
        <rev/>
        <date>2022-02-13</date>
        <source>PROGLOG01.kicad_sch</source>
        <comment number="1" value="open source toolchain FPGA"/>
        <comment number="2" value=""/>
        <comment number="3" value="Povik"/>
        <comment number="4" value=""/>
        <comment number="5" value=""/>
        <comment number="6" value=""/>
        <comment number="7" value=""/>
        <comment number="8" value=""/>
        <comment number="9" value=""/>
      </title_block>
    </sheet>
  </design>
  <components>
    <comp ref="C1">
      <value>100nF</value>
      <footprint>Capacitor_SMD:C_0805_2012Metric</footprint>
      <fields>
        <field name="UST_ID">5c70984712875079b91f8b4c</field>
      </fields>
      <libsource lib="Device" part="C" description="Unpolarized capacitor"/>
      <property name="UST_ID" value="5c70984712875079b91f8b4c"/>
      <property name="Sheetname" value=""/>
      <property name="Sheetfile" value="PROGLOG01.kicad_sch"/>
      <sheetpath names="/" tstamps="/"/>
      <tstamps>00000000-0000-0000-0000-00005db4d28c</tstamps>
    </comp>
    <comp ref="C2">
      <value>100nF</value>
      <footprint>Capacitor_SMD:C_0805_2012Metric</footprint>
      <fields>
        <field name="UST_ID">5c70984712875079b91f8b4c</field>
        <field name="UST_id">C0805_100n</field>
      </fields>
      <libsource lib="Device" part="C_Small" description="Unpolarized capacitor, small symbol"/>
      <property name="UST_id" value="C0805_100n"/>
      <property name="UST_ID" value="5c70984712875079b91f8b4c"/>
      <property name="Sheetname" value=""/>
      <property name="Sheetfile" value="PROGLOG01.kicad_sch"/>
      <sheetpath names="/" tstamps="/"/>
      <tstamps>00000000-0000-0000-0000-00005562302c</tstamps>
    </comp>
    <comp ref="C3">
      <value>10uF</value>
      <footprint>Capacitor_SMD:C_0805_2012Metric</footprint>
      <fields>
        <field name="UST_ID">5c70984812875079b91f8bbd</field>
      </fields>
      <libsource lib="Device" part="C_Polarized" description="Polarized capacitor"/>
      <property name="UST_ID" value="5c70984812875079b91f8bbd"/>
      <property name="Sheetname" value=""/>
      <property name="Sheetfile" value="PROGLOG01.kicad_sch"/>
      <sheetpath names="/" tstamps="/"/>
      <tstamps>00000000-0000-0000-0000-000055623093</tstamps>
    </comp>
    <comp ref="C4">
      <value>1uF</value>
      <footprint>Capacitor_SMD:C_0805_2012Metric</footprint>
      <fields>
        <field name="UST_ID">5c70984712875079b91f8b50</field>
      </fields>
      <libsource lib="Device" part="C" description="Unpolarized capacitor"/>
      <property name="UST_ID" value="5c70984712875079b91f8b50"/>
      <property name="Sheetname" value=""/>
      <property name="Sheetfile" value="PROGLOG01.kicad_sch"/>
      <sheetpath names="/" tstamps="/"/>
      <tstamps>00000000-0000-0000-0000-00005db54f12</tstamps>
    </comp>
    <comp ref="C5">
      <value>10uF</value>
      <footprint>Capacitor_SMD:C_0805_2012Metric</footprint>
      <fields>
        <field name="UST_ID">5c70984812875079b91f8bbd</field>
      </fields>
      <libsource lib="Device" part="C_Polarized" description="Polarized capacitor"/>
      <property name="UST_ID" value="5c70984812875079b91f8bbd"/>
      <property name="Sheetname" value=""/>
      <property name="Sheetfile" value="PROGLOG01.kicad_sch"/>
      <sheetpath names="/" tstamps="/"/>
      <tstamps>00000000-0000-0000-0000-00005dbd632c</tstamps>
    </comp>
    <comp ref="C6">
      <value>100nF</value>
      <footprint>Capacitor_SMD:C_0805_2012Metric</footprint>
      <fields>
        <field name="UST_ID">5c70984712875079b91f8b4c</field>
      </fields>
      <libsource lib="Device" part="C" description="Unpolarized capacitor"/>
      <property name="UST_ID" value="5c70984712875079b91f8b4c"/>
      <property name="Sheetname" value=""/>
      <property name="Sheetfile" value="PROGLOG01.kicad_sch"/>
      <sheetpath names="/" tstamps="/"/>
      <tstamps>00000000-0000-0000-0000-00005d8c65fd</tstamps>
    </comp>
    <comp ref="C7">
      <value>10nF</value>
      <footprint>Capacitor_SMD:C_0805_2012Metric</footprint>
      <fields>
        <field name="UST_ID">5c70984712875079b91f8b49</field>
      </fields>
      <libsource lib="Device" part="C" description="Unpolarized capacitor"/>
      <property name="UST_ID" value="5c70984712875079b91f8b49"/>
      <property name="Sheetname" value=""/>
      <property name="Sheetfile" value="PROGLOG01.kicad_sch"/>
      <sheetpath names="/" tstamps="/"/>
      <tstamps>00000000-0000-0000-0000-00005da72306</tstamps>
    </comp>
    <comp ref="C8">
      <value>100nF</value>
      <footprint>Capacitor_SMD:C_0805_2012Metric</footprint>
      <fields>
        <field name="UST_ID">5c70984712875079b91f8b4c</field>
      </fields>
      <libsource lib="Device" part="C" description="Unpolarized capacitor"/>
      <property name="UST_ID" value="5c70984712875079b91f8b4c"/>
      <property name="Sheetname" value=""/>
      <property name="Sheetfile" value="PROGLOG01.kicad_sch"/>
      <sheetpath names="/" tstamps="/"/>
      <tstamps>00000000-0000-0000-0000-00005db40afc</tstamps>
    </comp>
    <comp ref="C9">
      <value>100nF</value>
      <footprint>Capacitor_SMD:C_0805_2012Metric</footprint>
      <fields>
        <field name="UST_ID">5c70984712875079b91f8b4c</field>
      </fields>
      <libsource lib="Device" part="C" description="Unpolarized capacitor"/>
      <property name="UST_ID" value="5c70984712875079b91f8b4c"/>
      <property name="Sheetname" value=""/>
      <property name="Sheetfile" value="PROGLOG01.kicad_sch"/>
      <sheetpath names="/" tstamps="/"/>
      <tstamps>00000000-0000-0000-0000-00005db41ca5</tstamps>
    </comp>
    <comp ref="C10">
      <value>100nF</value>
      <footprint>Capacitor_SMD:C_0805_2012Metric</footprint>
      <fields>
        <field name="UST_ID">5c70984712875079b91f8b4c</field>
      </fields>
      <libsource lib="Device" part="C" description="Unpolarized capacitor"/>
      <property name="UST_ID" value="5c70984712875079b91f8b4c"/>
      <property name="Sheetname" value=""/>
      <property name="Sheetfile" value="PROGLOG01.kicad_sch"/>
      <sheetpath names="/" tstamps="/"/>
      <tstamps>00000000-0000-0000-0000-00005db5839b</tstamps>
    </comp>
    <comp ref="D1">
      <value>BZV55C-5,6V</value>
      <footprint>Mlab_D:Diode-MiniMELF_Standard</footprint>
      <fields>
        <field name="UST_ID">5c70984512875079b91f88b2</field>
      </fields>
      <libsource lib="MLAB_D" part="D_ZENER" description=""/>
      <property name="UST_ID" value="5c70984512875079b91f88b2"/>
      <property name="Sheetname" value=""/>
      <property name="Sheetfile" value="PROGLOG01.kicad_sch"/>
      <sheetpath names="/" tstamps="/"/>
      <tstamps>00000000-0000-0000-0000-00005b4de0b5</tstamps>
    </comp>
    <comp ref="D2">
      <value>YELLOW</value>
      <footprint>Mlab_D:LED_1206</footprint>
      <fields>
        <field name="UST_ID">5c70984412875079b91f8897</field>
      </fields>
      <libsource lib="Device" part="LED" description="Light emitting diode"/>
      <property name="UST_ID" value="5c70984412875079b91f8897"/>
      <property name="Sheetname" value=""/>
      <property name="Sheetfile" value="PROGLOG01.kicad_sch"/>
      <sheetpath names="/" tstamps="/"/>
      <tstamps>00000000-0000-0000-0000-00005d8d5bc0</tstamps>
    </comp>
    <comp ref="D3">
      <value>BLUE</value>
      <footprint>Mlab_D:LED_1206</footprint>
      <fields>
        <field name="UST_ID">5c70984512875079b91f8898</field>
      </fields>
      <libsource lib="Device" part="LED" description="Light emitting diode"/>
      <property name="UST_ID" value="5c70984512875079b91f8898"/>
      <property name="Sheetname" value=""/>
      <property name="Sheetfile" value="PROGLOG01.kicad_sch"/>
      <sheetpath names="/" tstamps="/"/>
      <tstamps>00000000-0000-0000-0000-00005d8d5b1b</tstamps>
    </comp>
    <comp ref="J1">
      <value>JUMP_3X2</value>
      <footprint>Mlab_Pin_Headers:Straight_2x03</footprint>
      <libsource lib="MLAB_Jumpers" part="JUMP_3X2" description="MLAB modified doubled pinheader connector"/>
      <property name="Sheetname" value=""/>
      <property name="Sheetfile" value="PROGLOG01.kicad_sch"/>
      <sheetpath names="/" tstamps="/"/>
      <tstamps>00000000-0000-0000-0000-00005b4dde60</tstamps>
    </comp>
    <comp ref="J2">
      <value>HEADER_2x01</value>
      <footprint>Mlab_Pin_Headers:Straight_2x01</footprint>
      <libsource lib="MLAB_HEADER" part="HEADER_2x01" description="2x01 2.54 mm pitch header"/>
      <property name="Sheetname" value=""/>
      <property name="Sheetfile" value="PROGLOG01.kicad_sch"/>
      <sheetpath names="/" tstamps="/"/>
      <tstamps>00000000-0000-0000-0000-00005e0f2c1b</tstamps>
    </comp>
    <comp ref="J3">
      <value>HEADER_2x02_PARALLEL</value>
      <footprint>Mlab_Pin_Headers:Straight_2x02</footprint>
      <libsource lib="MLAB_HEADER" part="HEADER_2x02_PARALLEL" description="2x02 2.54 mm pitch header, 2 pins next to each other are connected"/>
      <property name="Sheetname" value=""/>
      <property name="Sheetfile" value="PROGLOG01.kicad_sch"/>
      <sheetpath names="/" tstamps="/"/>
      <tstamps>00000000-0000-0000-0000-00005db90bea</tstamps>
    </comp>
    <comp ref="J4">
      <value>HEADER_2x04</value>
      <footprint>Mlab_Pin_Headers:Straight_2x04</footprint>
      <libsource lib="MLAB_HEADER" part="HEADER_2x04" description="2x04 2.54 mm pitch header"/>
      <property name="Sheetname" value=""/>
      <property name="Sheetfile" value="PROGLOG01.kicad_sch"/>
      <sheetpath names="/" tstamps="/"/>
      <tstamps>00000000-0000-0000-0000-00005da2ff1e</tstamps>
    </comp>
    <comp ref="J5">
      <value>HEADER_2x01_PARALLEL</value>
      <footprint>Mlab_Pin_Headers:Straight_2x01</footprint>
      <libsource lib="MLAB_HEADER" part="HEADER_2x01_PARALLEL" description="2x01 2.54 mm pitch header, 2 pins next to each other are connected"/>
      <property name="Sheetname" value=""/>
      <property name="Sheetfile" value="PROGLOG01.kicad_sch"/>
      <sheetpath names="/" tstamps="/"/>
      <tstamps>00000000-0000-0000-0000-00005db8b435</tstamps>
    </comp>
    <comp ref="J6">
      <value>HEADER_2x01_PARALLEL</value>
      <footprint>Mlab_Pin_Headers:Straight_2x01</footprint>
      <libsource lib="MLAB_HEADER" part="HEADER_2x01_PARALLEL" description="2x01 2.54 mm pitch header, 2 pins next to each other are connected"/>
      <property name="Sheetname" value=""/>
      <property name="Sheetfile" value="PROGLOG01.kicad_sch"/>
      <sheetpath names="/" tstamps="/"/>
      <tstamps>00000000-0000-0000-0000-00005db8b7ff</tstamps>
    </comp>
    <comp ref="J7">
      <value>HEADER_2x01_PARALLEL</value>
      <footprint>Mlab_Pin_Headers:Straight_2x01</footprint>
      <libsource lib="MLAB_HEADER" part="HEADER_2x01_PARALLEL" description="2x01 2.54 mm pitch header, 2 pins next to each other are connected"/>
      <property name="Sheetname" value=""/>
      <property name="Sheetfile" value="PROGLOG01.kicad_sch"/>
      <sheetpath names="/" tstamps="/"/>
      <tstamps>00000000-0000-0000-0000-00005db92eaf</tstamps>
    </comp>
    <comp ref="J8">
      <value>HEADER_2x01_PARALLEL</value>
      <footprint>Mlab_Pin_Headers:Straight_2x01</footprint>
      <libsource lib="MLAB_HEADER" part="HEADER_2x01_PARALLEL" description="2x01 2.54 mm pitch header, 2 pins next to each other are connected"/>
      <property name="Sheetname" value=""/>
      <property name="Sheetfile" value="PROGLOG01.kicad_sch"/>
      <sheetpath names="/" tstamps="/"/>
      <tstamps>00000000-0000-0000-0000-00005db9a561</tstamps>
    </comp>
    <comp ref="J9">
      <value>HEADER_2x01_PARALLEL</value>
      <footprint>Mlab_Pin_Headers:Straight_2x01</footprint>
      <libsource lib="MLAB_HEADER" part="HEADER_2x01_PARALLEL" description="2x01 2.54 mm pitch header, 2 pins next to each other are connected"/>
      <property name="Sheetname" value=""/>
      <property name="Sheetfile" value="PROGLOG01.kicad_sch"/>
      <sheetpath names="/" tstamps="/"/>
      <tstamps>00000000-0000-0000-0000-00005db96088</tstamps>
    </comp>
    <comp ref="J10">
      <value>HEADER_2x01_PARALLEL</value>
      <footprint>Mlab_Pin_Headers:Straight_2x01</footprint>
      <libsource lib="MLAB_HEADER" part="HEADER_2x01_PARALLEL" description="2x01 2.54 mm pitch header, 2 pins next to each other are connected"/>
      <property name="Sheetname" value=""/>
      <property name="Sheetfile" value="PROGLOG01.kicad_sch"/>
      <sheetpath names="/" tstamps="/"/>
      <tstamps>00000000-0000-0000-0000-00005db9e862</tstamps>
    </comp>
    <comp ref="J11">
      <value>HEADER_2x01_PARALLEL</value>
      <footprint>Mlab_Pin_Headers:Straight_2x01</footprint>
      <libsource lib="MLAB_HEADER" part="HEADER_2x01_PARALLEL" description="2x01 2.54 mm pitch header, 2 pins next to each other are connected"/>
      <property name="Sheetname" value=""/>
      <property name="Sheetfile" value="PROGLOG01.kicad_sch"/>
      <sheetpath names="/" tstamps="/"/>
      <tstamps>00000000-0000-0000-0000-00005dba7042</tstamps>
    </comp>
    <comp ref="J13">
      <value>HEADER_2x01_PARALLEL</value>
      <footprint>Mlab_Pin_Headers:Straight_2x01</footprint>
      <libsource lib="MLAB_HEADER" part="HEADER_2x01_PARALLEL" description="2x01 2.54 mm pitch header, 2 pins next to each other are connected"/>
      <property name="Sheetname" value=""/>
      <property name="Sheetfile" value="PROGLOG01.kicad_sch"/>
      <sheetpath names="/" tstamps="/"/>
      <tstamps>00000000-0000-0000-0000-00005dba1ca3</tstamps>
    </comp>
    <comp ref="J14">
      <value>HEADER_2x01_PARALLEL</value>
      <footprint>Mlab_Pin_Headers:Straight_2x01</footprint>
      <libsource lib="MLAB_HEADER" part="HEADER_2x01_PARALLEL" description="2x01 2.54 mm pitch header, 2 pins next to each other are connected"/>
      <property name="Sheetname" value=""/>
      <property name="Sheetfile" value="PROGLOG01.kicad_sch"/>
      <sheetpath names="/" tstamps="/"/>
      <tstamps>00000000-0000-0000-0000-00005dba9359</tstamps>
    </comp>
    <comp ref="J15">
      <value>HEADER_2x01_PARALLEL</value>
      <footprint>Mlab_Pin_Headers:Straight_2x01</footprint>
      <libsource lib="MLAB_HEADER" part="HEADER_2x01_PARALLEL" description="2x01 2.54 mm pitch header, 2 pins next to each other are connected"/>
      <property name="Sheetname" value=""/>
      <property name="Sheetfile" value="PROGLOG01.kicad_sch"/>
      <sheetpath names="/" tstamps="/"/>
      <tstamps>00000000-0000-0000-0000-00005da7e83f</tstamps>
    </comp>
    <comp ref="J16">
      <value>HEADER_2x01_PARALLEL</value>
      <footprint>Mlab_Pin_Headers:Straight_2x01</footprint>
      <libsource lib="MLAB_HEADER" part="HEADER_2x01_PARALLEL" description="2x01 2.54 mm pitch header, 2 pins next to each other are connected"/>
      <property name="Sheetname" value=""/>
      <property name="Sheetfile" value="PROGLOG01.kicad_sch"/>
      <sheetpath names="/" tstamps="/"/>
      <tstamps>00000000-0000-0000-0000-00005da85290</tstamps>
    </comp>
    <comp ref="J17">
      <value>HEADER_2x01_PARALLEL</value>
      <footprint>Mlab_Pin_Headers:Straight_2x01</footprint>
      <libsource lib="MLAB_HEADER" part="HEADER_2x01_PARALLEL" description="2x01 2.54 mm pitch header, 2 pins next to each other are connected"/>
      <property name="Sheetname" value=""/>
      <property name="Sheetfile" value="PROGLOG01.kicad_sch"/>
      <sheetpath names="/" tstamps="/"/>
      <tstamps>00000000-0000-0000-0000-00005da85297</tstamps>
    </comp>
    <comp ref="J18">
      <value>HEADER_2x01_PARALLEL</value>
      <footprint>Mlab_Pin_Headers:Straight_2x01</footprint>
      <libsource lib="MLAB_HEADER" part="HEADER_2x01_PARALLEL" description="2x01 2.54 mm pitch header, 2 pins next to each other are connected"/>
      <property name="Sheetname" value=""/>
      <property name="Sheetfile" value="PROGLOG01.kicad_sch"/>
      <sheetpath names="/" tstamps="/"/>
      <tstamps>00000000-0000-0000-0000-00005da8529e</tstamps>
    </comp>
    <comp ref="J19">
      <value>HEADER_2x01_PARALLEL</value>
      <footprint>Mlab_Pin_Headers:Straight_2x01</footprint>
      <libsource lib="MLAB_HEADER" part="HEADER_2x01_PARALLEL" description="2x01 2.54 mm pitch header, 2 pins next to each other are connected"/>
      <property name="Sheetname" value=""/>
      <property name="Sheetfile" value="PROGLOG01.kicad_sch"/>
      <sheetpath names="/" tstamps="/"/>
      <tstamps>00000000-0000-0000-0000-00005da852a5</tstamps>
    </comp>
    <comp ref="J20">
      <value>HEADER_2x01_PARALLEL</value>
      <footprint>Mlab_Pin_Headers:Straight_2x01</footprint>
      <libsource lib="MLAB_HEADER" part="HEADER_2x01_PARALLEL" description="2x01 2.54 mm pitch header, 2 pins next to each other are connected"/>
      <property name="Sheetname" value=""/>
      <property name="Sheetfile" value="PROGLOG01.kicad_sch"/>
      <sheetpath names="/" tstamps="/"/>
      <tstamps>00000000-0000-0000-0000-00005da852ac</tstamps>
    </comp>
    <comp ref="J21">
      <value>HEADER_2x01_PARALLEL</value>
      <footprint>Mlab_Pin_Headers:Straight_2x01</footprint>
      <libsource lib="MLAB_HEADER" part="HEADER_2x01_PARALLEL" description="2x01 2.54 mm pitch header, 2 pins next to each other are connected"/>
      <property name="Sheetname" value=""/>
      <property name="Sheetfile" value="PROGLOG01.kicad_sch"/>
      <sheetpath names="/" tstamps="/"/>
      <tstamps>00000000-0000-0000-0000-00005da8c249</tstamps>
    </comp>
    <comp ref="J22">
      <value>HEADER_2x01_PARALLEL</value>
      <footprint>Mlab_Pin_Headers:Straight_2x01</footprint>
      <libsource lib="MLAB_HEADER" part="HEADER_2x01_PARALLEL" description="2x01 2.54 mm pitch header, 2 pins next to each other are connected"/>
      <property name="Sheetname" value=""/>
      <property name="Sheetfile" value="PROGLOG01.kicad_sch"/>
      <sheetpath names="/" tstamps="/"/>
      <tstamps>00000000-0000-0000-0000-00005da8c250</tstamps>
    </comp>
    <comp ref="J23">
      <value>HEADER_2x01_PARALLEL</value>
      <footprint>Mlab_Pin_Headers:Straight_2x01</footprint>
      <libsource lib="MLAB_HEADER" part="HEADER_2x01_PARALLEL" description="2x01 2.54 mm pitch header, 2 pins next to each other are connected"/>
      <property name="Sheetname" value=""/>
      <property name="Sheetfile" value="PROGLOG01.kicad_sch"/>
      <sheetpath names="/" tstamps="/"/>
      <tstamps>00000000-0000-0000-0000-00005da8c257</tstamps>
    </comp>
    <comp ref="J24">
      <value>HEADER_2x01_PARALLEL</value>
      <footprint>Mlab_Pin_Headers:Straight_2x01</footprint>
      <libsource lib="MLAB_HEADER" part="HEADER_2x01_PARALLEL" description="2x01 2.54 mm pitch header, 2 pins next to each other are connected"/>
      <property name="Sheetname" value=""/>
      <property name="Sheetfile" value="PROGLOG01.kicad_sch"/>
      <sheetpath names="/" tstamps="/"/>
      <tstamps>00000000-0000-0000-0000-00005da8c25e</tstamps>
    </comp>
    <comp ref="J25">
      <value>HEADER_2x01_PARALLEL</value>
      <footprint>Mlab_Pin_Headers:Straight_2x01</footprint>
      <libsource lib="MLAB_HEADER" part="HEADER_2x01_PARALLEL" description="2x01 2.54 mm pitch header, 2 pins next to each other are connected"/>
      <property name="Sheetname" value=""/>
      <property name="Sheetfile" value="PROGLOG01.kicad_sch"/>
      <sheetpath names="/" tstamps="/"/>
      <tstamps>00000000-0000-0000-0000-00005da8c265</tstamps>
    </comp>
    <comp ref="J26">
      <value>SATA</value>
      <footprint>MOLEX_67491-1030</footprint>
      <fields>
        <field name="UST_ID">5c70984712875079b91f8a7b</field>
      </fields>
      <libsource lib="MLAB_CONNECTORS" part="SATA" description=""/>
      <property name="UST_ID" value="5c70984712875079b91f8a7b"/>
      <property name="Sheetname" value=""/>
      <property name="Sheetfile" value="PROGLOG01.kicad_sch"/>
      <sheetpath names="/" tstamps="/"/>
      <tstamps>00000000-0000-0000-0000-00005dc4b4c2</tstamps>
    </comp>
    <comp ref="J27">
      <value>HEADER_2x01_PARALLEL</value>
      <footprint>Mlab_Pin_Headers:Straight_2x01</footprint>
      <libsource lib="MLAB_HEADER" part="HEADER_2x01_PARALLEL" description="2x01 2.54 mm pitch header, 2 pins next to each other are connected"/>
      <property name="Sheetname" value=""/>
      <property name="Sheetfile" value="PROGLOG01.kicad_sch"/>
      <sheetpath names="/" tstamps="/"/>
      <tstamps>00000000-0000-0000-0000-00005db17a62</tstamps>
    </comp>
    <comp ref="J28">
      <value>HEADER_2x01_PARALLEL</value>
      <footprint>Mlab_Pin_Headers:Straight_2x01</footprint>
      <libsource lib="MLAB_HEADER" part="HEADER_2x01_PARALLEL" description="2x01 2.54 mm pitch header, 2 pins next to each other are connected"/>
      <property name="Sheetname" value=""/>
      <property name="Sheetfile" value="PROGLOG01.kicad_sch"/>
      <sheetpath names="/" tstamps="/"/>
      <tstamps>00000000-0000-0000-0000-00005db1ecba</tstamps>
    </comp>
    <comp ref="J29">
      <value>HEADER_2x01_PARALLEL</value>
      <footprint>Mlab_Pin_Headers:Straight_2x01</footprint>
      <libsource lib="MLAB_HEADER" part="HEADER_2x01_PARALLEL" description="2x01 2.54 mm pitch header, 2 pins next to each other are connected"/>
      <property name="Sheetname" value=""/>
      <property name="Sheetfile" value="PROGLOG01.kicad_sch"/>
      <sheetpath names="/" tstamps="/"/>
      <tstamps>00000000-0000-0000-0000-00005db6d6c2</tstamps>
    </comp>
    <comp ref="J30">
      <value>HEADER_2x01_PARALLEL</value>
      <footprint>Mlab_Pin_Headers:Straight_2x01</footprint>
      <libsource lib="MLAB_HEADER" part="HEADER_2x01_PARALLEL" description="2x01 2.54 mm pitch header, 2 pins next to each other are connected"/>
      <property name="Sheetname" value=""/>
      <property name="Sheetfile" value="PROGLOG01.kicad_sch"/>
      <sheetpath names="/" tstamps="/"/>
      <tstamps>00000000-0000-0000-0000-00005db6d6c9</tstamps>
    </comp>
    <comp ref="J31">
      <value>HEADER_2x01_PARALLEL</value>
      <footprint>Mlab_Pin_Headers:Straight_2x01</footprint>
      <libsource lib="MLAB_HEADER" part="HEADER_2x01_PARALLEL" description="2x01 2.54 mm pitch header, 2 pins next to each other are connected"/>
      <property name="Sheetname" value=""/>
      <property name="Sheetfile" value="PROGLOG01.kicad_sch"/>
      <sheetpath names="/" tstamps="/"/>
      <tstamps>00000000-0000-0000-0000-00005db748eb</tstamps>
    </comp>
    <comp ref="J32">
      <value>HEADER_2x01_PARALLEL</value>
      <footprint>Mlab_Pin_Headers:Straight_2x01</footprint>
      <libsource lib="MLAB_HEADER" part="HEADER_2x01_PARALLEL" description="2x01 2.54 mm pitch header, 2 pins next to each other are connected"/>
      <property name="Sheetname" value=""/>
      <property name="Sheetfile" value="PROGLOG01.kicad_sch"/>
      <sheetpath names="/" tstamps="/"/>
      <tstamps>00000000-0000-0000-0000-00005db748f2</tstamps>
    </comp>
    <comp ref="J33">
      <value>HEADER_2x01_PARALLEL</value>
      <footprint>Mlab_Pin_Headers:Straight_2x01</footprint>
      <libsource lib="MLAB_HEADER" part="HEADER_2x01_PARALLEL" description="2x01 2.54 mm pitch header, 2 pins next to each other are connected"/>
      <property name="Sheetname" value=""/>
      <property name="Sheetfile" value="PROGLOG01.kicad_sch"/>
      <sheetpath names="/" tstamps="/"/>
      <tstamps>00000000-0000-0000-0000-00005db7bd67</tstamps>
    </comp>
    <comp ref="J34">
      <value>HEADER_2x01_PARALLEL</value>
      <footprint>Mlab_Pin_Headers:Straight_2x01</footprint>
      <libsource lib="MLAB_HEADER" part="HEADER_2x01_PARALLEL" description="2x01 2.54 mm pitch header, 2 pins next to each other are connected"/>
      <property name="Sheetname" value=""/>
      <property name="Sheetfile" value="PROGLOG01.kicad_sch"/>
      <sheetpath names="/" tstamps="/"/>
      <tstamps>00000000-0000-0000-0000-00005db7bd6e</tstamps>
    </comp>
    <comp ref="M1">
      <value>HOLE</value>
      <footprint>Mlab_Mechanical:MountingHole_3mm</footprint>
      <libsource lib="MLAB_MECHANICAL" part="HOLE" description=""/>
      <property name="Sheetname" value=""/>
      <property name="Sheetfile" value="PROGLOG01.kicad_sch"/>
      <sheetpath names="/" tstamps="/"/>
      <tstamps>00000000-0000-0000-0000-0000549d7549</tstamps>
    </comp>
    <comp ref="M2">
      <value>HOLE</value>
      <footprint>Mlab_Mechanical:MountingHole_3mm</footprint>
      <libsource lib="MLAB_MECHANICAL" part="HOLE" description=""/>
      <property name="Sheetname" value=""/>
      <property name="Sheetfile" value="PROGLOG01.kicad_sch"/>
      <sheetpath names="/" tstamps="/"/>
      <tstamps>00000000-0000-0000-0000-0000549d7628</tstamps>
    </comp>
    <comp ref="M3">
      <value>HOLE</value>
      <footprint>Mlab_Mechanical:MountingHole_3mm</footprint>
      <libsource lib="MLAB_MECHANICAL" part="HOLE" description=""/>
      <property name="Sheetname" value=""/>
      <property name="Sheetfile" value="PROGLOG01.kicad_sch"/>
      <sheetpath names="/" tstamps="/"/>
      <tstamps>00000000-0000-0000-0000-0000549d7646</tstamps>
    </comp>
    <comp ref="M4">
      <value>HOLE</value>
      <footprint>Mlab_Mechanical:MountingHole_3mm</footprint>
      <libsource lib="MLAB_MECHANICAL" part="HOLE" description=""/>
      <property name="Sheetname" value=""/>
      <property name="Sheetfile" value="PROGLOG01.kicad_sch"/>
      <sheetpath names="/" tstamps="/"/>
      <tstamps>00000000-0000-0000-0000-0000549d7665</tstamps>
    </comp>
    <comp ref="R1">
      <value>10k</value>
      <footprint>Resistor_SMD:R_0805_2012Metric</footprint>
      <fields>
        <field name="UST_ID">5c70984612875079b91f899f</field>
      </fields>
      <libsource lib="Device" part="R" description="Resistor"/>
      <property name="UST_ID" value="5c70984612875079b91f899f"/>
      <property name="Sheetname" value=""/>
      <property name="Sheetfile" value="PROGLOG01.kicad_sch"/>
      <sheetpath names="/" tstamps="/"/>
      <tstamps>00000000-0000-0000-0000-00005e10e9a6</tstamps>
    </comp>
    <comp ref="R2">
      <value>0R</value>
      <footprint>Resistor_SMD:R_0805_2012Metric</footprint>
      <fields>
        <field name="UST_ID">5c70984512875079b91f896b</field>
      </fields>
      <libsource lib="Device" part="R" description="Resistor"/>
      <property name="UST_ID" value="5c70984512875079b91f896b"/>
      <property name="Sheetname" value=""/>
      <property name="Sheetfile" value="PROGLOG01.kicad_sch"/>
      <sheetpath names="/" tstamps="/"/>
      <tstamps>00000000-0000-0000-0000-00005dbb9f9c</tstamps>
    </comp>
    <comp ref="R3">
      <value>0R</value>
      <footprint>Resistor_SMD:R_0805_2012Metric</footprint>
      <fields>
        <field name="UST_ID">5c70984512875079b91f896b</field>
      </fields>
      <libsource lib="Device" part="R" description="Resistor"/>
      <property name="UST_ID" value="5c70984512875079b91f896b"/>
      <property name="Sheetname" value=""/>
      <property name="Sheetfile" value="PROGLOG01.kicad_sch"/>
      <sheetpath names="/" tstamps="/"/>
      <tstamps>00000000-0000-0000-0000-00005dbba094</tstamps>
    </comp>
    <comp ref="R4">
      <value>100R</value>
      <footprint>Resistor_SMD:R_0805_2012Metric</footprint>
      <fields>
        <field name="UST_ID">5c70984512875079b91f8977</field>
      </fields>
      <libsource lib="Device" part="R" description="Resistor"/>
      <property name="UST_ID" value="5c70984512875079b91f8977"/>
      <property name="Sheetname" value=""/>
      <property name="Sheetfile" value="PROGLOG01.kicad_sch"/>
      <sheetpath names="/" tstamps="/"/>
      <tstamps>00000000-0000-0000-0000-00005d8c5587</tstamps>
    </comp>
    <comp ref="R5">
      <value>10k</value>
      <footprint>Resistor_SMD:R_0805_2012Metric</footprint>
      <fields>
        <field name="UST_ID">5c70984612875079b91f899f</field>
      </fields>
      <libsource lib="Device" part="R" description="Resistor"/>
      <property name="UST_ID" value="5c70984612875079b91f899f"/>
      <property name="Sheetname" value=""/>
      <property name="Sheetfile" value="PROGLOG01.kicad_sch"/>
      <sheetpath names="/" tstamps="/"/>
      <tstamps>00000000-0000-0000-0000-00005d98fe0c</tstamps>
    </comp>
    <comp ref="R6">
      <value>10k</value>
      <footprint>Resistor_SMD:R_0805_2012Metric</footprint>
      <fields>
        <field name="UST_ID">5c70984612875079b91f899f</field>
      </fields>
      <libsource lib="Device" part="R" description="Resistor"/>
      <property name="UST_ID" value="5c70984612875079b91f899f"/>
      <property name="Sheetname" value=""/>
      <property name="Sheetfile" value="PROGLOG01.kicad_sch"/>
      <sheetpath names="/" tstamps="/"/>
      <tstamps>00000000-0000-0000-0000-00005da42e0b</tstamps>
    </comp>
    <comp ref="R7">
      <value>100R</value>
      <footprint>Resistor_SMD:R_0805_2012Metric</footprint>
      <fields>
        <field name="UST_ID">5c70984512875079b91f8977</field>
      </fields>
      <libsource lib="Device" part="R" description="Resistor"/>
      <property name="UST_ID" value="5c70984512875079b91f8977"/>
      <property name="Sheetname" value=""/>
      <property name="Sheetfile" value="PROGLOG01.kicad_sch"/>
      <sheetpath names="/" tstamps="/"/>
      <tstamps>00000000-0000-0000-0000-00005dcf334f</tstamps>
    </comp>
    <comp ref="R8">
      <value>100R</value>
      <footprint>Resistor_SMD:R_0805_2012Metric</footprint>
      <fields>
        <field name="UST_ID">5c70984512875079b91f8977</field>
      </fields>
      <libsource lib="Device" part="R" description="Resistor"/>
      <property name="UST_ID" value="5c70984512875079b91f8977"/>
      <property name="Sheetname" value=""/>
      <property name="Sheetfile" value="PROGLOG01.kicad_sch"/>
      <sheetpath names="/" tstamps="/"/>
      <tstamps>00000000-0000-0000-0000-00005dcdb9b6</tstamps>
    </comp>
    <comp ref="R9">
      <value>200R</value>
      <footprint>Resistor_SMD:R_0805_2012Metric</footprint>
      <fields>
        <field name="UST_ID">5c70984512875079b91f897d</field>
      </fields>
      <libsource lib="Device" part="R" description="Resistor"/>
      <property name="UST_ID" value="5c70984512875079b91f897d"/>
      <property name="Sheetname" value=""/>
      <property name="Sheetfile" value="PROGLOG01.kicad_sch"/>
      <sheetpath names="/" tstamps="/"/>
      <tstamps>00000000-0000-0000-0000-00005d8d8e38</tstamps>
    </comp>
    <comp ref="R10">
      <value>200R</value>
      <footprint>Resistor_SMD:R_0805_2012Metric</footprint>
      <fields>
        <field name="UST_ID">5c70984512875079b91f897d</field>
      </fields>
      <libsource lib="Device" part="R" description="Resistor"/>
      <property name="UST_ID" value="5c70984512875079b91f897d"/>
      <property name="Sheetname" value=""/>
      <property name="Sheetfile" value="PROGLOG01.kicad_sch"/>
      <sheetpath names="/" tstamps="/"/>
      <tstamps>00000000-0000-0000-0000-00005d8d8ead</tstamps>
    </comp>
    <comp ref="SW1">
      <value>SW_Push</value>
      <footprint>Mlab_SW:SW_PUSH_SMALL</footprint>
      <fields>
        <field name="UST_ID">5c70984712875079b91f8ad1</field>
      </fields>
      <libsource lib="Switch" part="SW_Push" description="Push button switch, generic, two pins"/>
      <property name="UST_ID" value="5c70984712875079b91f8ad1"/>
      <property name="Sheetname" value=""/>
      <property name="Sheetfile" value="PROGLOG01.kicad_sch"/>
      <sheetpath names="/" tstamps="/"/>
      <tstamps>00000000-0000-0000-0000-00005da31d36</tstamps>
    </comp>
    <comp ref="U1">
      <value>TPS22919DCK</value>
      <footprint>Package_TO_SOT_SMD:SOT-363_SC-70-6_Handsoldering</footprint>
      <datasheet>https://www.ti.com/lit/ds/symlink/tps22919.pdf</datasheet>
      <fields>
        <field name="UST_ID">5dc501ee128750448eca1add</field>
      </fields>
      <libsource lib="MLAB_IO" part="TPS22919DCK" description=""/>
      <property name="UST_ID" value="5dc501ee128750448eca1add"/>
      <property name="Sheetname" value=""/>
      <property name="Sheetfile" value="PROGLOG01.kicad_sch"/>
      <sheetpath names="/" tstamps="/"/>
      <tstamps>00000000-0000-0000-0000-00005dc93e5c</tstamps>
    </comp>
    <comp ref="U2">
      <value>MIC5504-1.2YM5</value>
      <footprint>Package_TO_SOT_SMD:SOT-23-5</footprint>
      <datasheet>http://ww1.microchip.com/downloads/en/DeviceDoc/MIC550X.pdf</datasheet>
      <fields>
        <field name="UST_ID">5dc5036e128750448eca1af0</field>
      </fields>
      <libsource lib="Regulator_Linear" part="MIC5504-1.2YM5" description="300mA Low-dropout Voltage Regulator, Vout 1.2V, Vin up to 5.5V, SOT-23"/>
      <property name="UST_ID" value="5dc5036e128750448eca1af0"/>
      <property name="Sheetname" value=""/>
      <property name="Sheetfile" value="PROGLOG01.kicad_sch"/>
      <sheetpath names="/" tstamps="/"/>
      <tstamps>00000000-0000-0000-0000-00005db46f40</tstamps>
    </comp>
    <comp ref="U3">
      <value>AT25SF081-SSH</value>
      <footprint>Package_SO:SOIC-8_3.9x4.9mm_P1.27mm</footprint>
      <datasheet>https://www.adestotech.com/wp-content/uploads/DS-AT25SF081_045.pdf</datasheet>
      <fields>
        <field name="UST_ID">5dc503e8128750448eca1b04</field>
      </fields>
      <libsource lib="Memory_Flash" part="AT25SF081-SSHD-X" description="8-Mbit, 2.5V Minimum SPI Serial Flash Memory with Dual-I/O and Quad-I/O Support, SOIC-8"/>
      <property name="UST_ID" value="5dc503e8128750448eca1b04"/>
      <property name="Sheetname" value=""/>
      <property name="Sheetfile" value="PROGLOG01.kicad_sch"/>
      <sheetpath names="/" tstamps="/"/>
      <tstamps>00000000-0000-0000-0000-00005e086457</tstamps>
    </comp>
    <comp ref="U4">
      <value>ICE40UP5K-SG48I</value>
      <footprint>Package_DFN_QFN:QFN-48-1EP_7x7mm_P0.5mm_EP5.6x5.6mm</footprint>
      <datasheet>http://www.latticesemi.com/Products/FPGAandCPLD/iCE40Ultra</datasheet>
      <fields>
        <field name="UST_ID">5dc504cb128750448eca1b12</field>
      </fields>
      <libsource lib="FPGA_Lattice" part="ICE40UP5K-SG48ITR" description="iCE40 UltraPlus FPGA, 5280 LUTs, 1.2V, 48-pin QFN"/>
      <property name="UST_ID" value="5dc504cb128750448eca1b12"/>
      <property name="Sheetname" value=""/>
      <property name="Sheetfile" value="PROGLOG01.kicad_sch"/>
      <sheetpath names="/" tstamps="/"/>
      <tstamps>00000000-0000-0000-0000-00005d8c3df4 00000000-0000-0000-0000-00005d8c3d71 00000000-0000-0000-0000-00005d8c3e7c 00000000-0000-0000-0000-00005d8c3cd5</tstamps>
    </comp>
    <comp ref="X1">
      <value>ISM92-3351AH24.00</value>
      <footprint>Oscillator:Oscillator_SMD_EuroQuartz_XO91-4Pin_7.0x5.0mm</footprint>
      <datasheet>http://cdn-reichelt.de/documents/datenblatt/B400/XO91.pdf</datasheet>
      <fields>
        <field name="UST_ID">5c70984712875079b91f8b18</field>
      </fields>
      <libsource lib="Oscillator" part="XO91" description="HCMOS Clock Oscillator"/>
      <property name="UST_ID" value="5c70984712875079b91f8b18"/>
      <property name="Sheetname" value=""/>
      <property name="Sheetfile" value="PROGLOG01.kicad_sch"/>
      <sheetpath names="/" tstamps="/"/>
      <tstamps>00000000-0000-0000-0000-00005da56edd</tstamps>
    </comp>
  </components>
  <libparts>
    <libpart lib="Device" part="C">
      <description>Unpolarized capacitor</description>
      <docs>~</docs>
      <footprints>
        <fp>C_*</fp>
      </footprints>
      <fields>
        <field name="Reference">C</field>
        <field name="Value">C</field>
        <field name="Datasheet">~</field>
      </fields>
      <pins>
        <pin num="1" name="" type="passive"/>
        <pin num="2" name="" type="passive"/>
      </pins>
    </libpart>
    <libpart lib="Device" part="C_Polarized">
      <description>Polarized capacitor</description>
      <docs>~</docs>
      <footprints>
        <fp>CP_*</fp>
      </footprints>
      <fields>
        <field name="Reference">C</field>
        <field name="Value">C_Polarized</field>
        <field name="Datasheet">~</field>
      </fields>
      <pins>
        <pin num="1" name="" type="passive"/>
        <pin num="2" name="" type="passive"/>
      </pins>
    </libpart>
    <libpart lib="Device" part="C_Small">
      <description>Unpolarized capacitor, small symbol</description>
      <docs>~</docs>
      <footprints>
        <fp>C_*</fp>
      </footprints>
      <fields>
        <field name="Reference">C</field>
        <field name="Value">C_Small</field>
        <field name="Datasheet">~</field>
      </fields>
      <pins>
        <pin num="1" name="" type="passive"/>
        <pin num="2" name="" type="passive"/>
      </pins>
    </libpart>
    <libpart lib="Device" part="LED">
      <description>Light emitting diode</description>
      <docs>~</docs>
      <footprints>
        <fp>LED*</fp>
        <fp>LED_SMD:*</fp>
        <fp>LED_THT:*</fp>
      </footprints>
      <fields>
        <field name="Reference">D</field>
        <field name="Value">LED</field>
        <field name="Datasheet">~</field>
      </fields>
      <pins>
        <pin num="1" name="K" type="passive"/>
        <pin num="2" name="A" type="passive"/>
      </pins>
    </libpart>
    <libpart lib="Device" part="R">
      <description>Resistor</description>
      <docs>~</docs>
      <footprints>
        <fp>R_*</fp>
      </footprints>
      <fields>
        <field name="Reference">R</field>
        <field name="Value">R</field>
        <field name="Datasheet">~</field>
      </fields>
      <pins>
        <pin num="1" name="" type="passive"/>
        <pin num="2" name="" type="passive"/>
      </pins>
    </libpart>
    <libpart lib="FPGA_Lattice" part="ICE40UP5K-SG48ITR">
      <description>iCE40 UltraPlus FPGA, 5280 LUTs, 1.2V, 48-pin QFN</description>
      <docs>http://www.latticesemi.com/Products/FPGAandCPLD/iCE40Ultra</docs>
      <footprints>
        <fp>QFN*7x7mm*P0.5mm*EP5.6x5.6mm*</fp>
      </footprints>
      <fields>
        <field name="Reference">U</field>
        <field name="Value">ICE40UP5K-SG48ITR</field>
        <field name="Footprint">Package_DFN_QFN:QFN-48-1EP_7x7mm_P0.5mm_EP5.6x5.6mm</field>
        <field name="Datasheet">http://www.latticesemi.com/Products/FPGAandCPLD/iCE40Ultra</field>
      </fields>
      <pins>
        <pin num="1" name="VCCIO_2" type="power_in"/>
        <pin num="2" name="IOB_6a" type="bidirectional"/>
        <pin num="3" name="IOB_9b" type="bidirectional"/>
        <pin num="4" name="IOB_8a" type="bidirectional"/>
        <pin num="5" name="VCC" type="power_in"/>
        <pin num="6" name="IOB_13b" type="bidirectional"/>
        <pin num="7" name="CDONE" type="open_collector"/>
        <pin num="8" name="~{CRESET}" type="input"/>
        <pin num="9" name="IOB_16a" type="bidirectional"/>
        <pin num="10" name="IOB_18a" type="bidirectional"/>
        <pin num="11" name="IOB_20a" type="bidirectional"/>
        <pin num="12" name="IOB_22b" type="bidirectional"/>
        <pin num="13" name="IOB_24a" type="bidirectional"/>
        <pin num="14" name="IOB_32a_SPI_SO" type="bidirectional"/>
        <pin num="15" name="IOB_34a_SPI_SCK" type="bidirectional"/>
        <pin num="16" name="IOB_35b_SPI_SS" type="bidirectional"/>
        <pin num="17" name="IOB_33b_SPI_SI" type="bidirectional"/>
        <pin num="18" name="IOB_31b" type="bidirectional"/>
        <pin num="19" name="IOB_29b" type="bidirectional"/>
        <pin num="20" name="IOB_25b_G3" type="bidirectional"/>
        <pin num="21" name="IOB_23b" type="bidirectional"/>
        <pin num="22" name="SPI_VCCIO1" type="power_in"/>
        <pin num="23" name="IOT_37a" type="bidirectional"/>
        <pin num="24" name="VPP_2V5" type="power_in"/>
        <pin num="25" name="IOT_36b" type="bidirectional"/>
        <pin num="26" name="IOT_39a" type="bidirectional"/>
        <pin num="27" name="IOT_38b" type="bidirectional"/>
        <pin num="28" name="IOT_41a" type="bidirectional"/>
        <pin num="29" name="VCCPLL" type="power_out"/>
        <pin num="30" name="VCC" type="passive"/>
        <pin num="31" name="IOT_42b" type="bidirectional"/>
        <pin num="32" name="IOT_43a" type="bidirectional"/>
        <pin num="33" name="VCCIO_0" type="power_in"/>
        <pin num="34" name="IOT_44b" type="bidirectional"/>
        <pin num="35" name="IOT_46b_G0" type="bidirectional"/>
        <pin num="36" name="IOT_48b" type="bidirectional"/>
        <pin num="37" name="IOT_45a_G1" type="bidirectional"/>
        <pin num="38" name="IOT_50b" type="bidirectional"/>
        <pin num="39" name="RGB0" type="open_collector"/>
        <pin num="40" name="RGB1" type="open_collector"/>
        <pin num="41" name="RGB2" type="open_collector"/>
        <pin num="42" name="IOT_51a" type="bidirectional"/>
        <pin num="43" name="IOT_49a" type="bidirectional"/>
        <pin num="44" name="IOB_3b_G6" type="bidirectional"/>
        <pin num="45" name="IOB_5b" type="bidirectional"/>
        <pin num="46" name="IOB_0a" type="bidirectional"/>
        <pin num="47" name="IOB_2a" type="bidirectional"/>
        <pin num="48" name="IOB_4a" type="bidirectional"/>
        <pin num="49" name="GND" type="power_in"/>
      </pins>
    </libpart>
    <libpart lib="MLAB_CONNECTORS" part="SATA">
      <fields>
        <field name="Reference">J</field>
        <field name="Value">SATA</field>
        <field name="Footprint">MOLEX_67491-1030</field>
      </fields>
      <pins>
        <pin num="1" name="1" type="passive"/>
        <pin num="2" name="2" type="passive"/>
        <pin num="3" name="3" type="passive"/>
        <pin num="4" name="4" type="passive"/>
        <pin num="5" name="5" type="passive"/>
        <pin num="6" name="6" type="passive"/>
        <pin num="7" name="7" type="passive"/>
      </pins>
    </libpart>
    <libpart lib="MLAB_D" part="D_ZENER">
      <footprints>
        <fp>D?</fp>
        <fp>SO*</fp>
        <fp>SM*</fp>
      </footprints>
      <fields>
        <field name="Reference">D</field>
        <field name="Value">D_ZENER</field>
      </fields>
      <pins>
        <pin num="1" name="K" type="passive"/>
        <pin num="2" name="A" type="passive"/>
      </pins>
    </libpart>
    <libpart lib="MLAB_HEADER" part="HEADER_2x01">
      <description>2x01 2.54 mm pitch header</description>
      <fields>
        <field name="Reference">J</field>
        <field name="Value">HEADER_2x01</field>
      </fields>
      <pins>
        <pin num="1" name="" type="input"/>
        <pin num="2" name="" type="input"/>
      </pins>
    </libpart>
    <libpart lib="MLAB_HEADER" part="HEADER_2x01_PARALLEL">
      <description>2x01 2.54 mm pitch header, 2 pins next to each other are connected</description>
      <fields>
        <field name="Reference">J</field>
        <field name="Value">HEADER_2x01_PARALLEL</field>
      </fields>
      <pins>
        <pin num="1" name="" type="input"/>
        <pin num="2" name="" type="input"/>
      </pins>
    </libpart>
    <libpart lib="MLAB_HEADER" part="HEADER_2x02_PARALLEL">
      <description>2x02 2.54 mm pitch header, 2 pins next to each other are connected</description>
      <fields>
        <field name="Reference">J</field>
        <field name="Value">HEADER_2x02_PARALLEL</field>
      </fields>
      <pins>
        <pin num="1" name="" type="input"/>
        <pin num="2" name="" type="input"/>
        <pin num="3" name="" type="input"/>
        <pin num="4" name="" type="input"/>
      </pins>
    </libpart>
    <libpart lib="MLAB_HEADER" part="HEADER_2x04">
      <description>2x04 2.54 mm pitch header</description>
      <fields>
        <field name="Reference">J</field>
        <field name="Value">HEADER_2x04</field>
      </fields>
      <pins>
        <pin num="1" name="" type="input"/>
        <pin num="2" name="" type="input"/>
        <pin num="3" name="" type="input"/>
        <pin num="4" name="" type="input"/>
        <pin num="5" name="" type="input"/>
        <pin num="6" name="" type="input"/>
        <pin num="7" name="" type="input"/>
        <pin num="8" name="" type="input"/>
      </pins>
    </libpart>
    <libpart lib="MLAB_IO" part="TPS22919DCK">
      <fields>
        <field name="Reference">U</field>
        <field name="Value">TPS22919DCK</field>
      </fields>
      <pins>
        <pin num="1" name="IN" type="power_in"/>
        <pin num="2" name="GND" type="input"/>
        <pin num="3" name="ON" type="input"/>
        <pin num="5" name="QOD" type="bidirectional"/>
        <pin num="6" name="OUT" type="power_out"/>
      </pins>
    </libpart>
    <libpart lib="MLAB_Jumpers" part="JUMP_3X2">
      <description>MLAB modified doubled pinheader connector</description>
      <fields>
        <field name="Reference">J</field>
        <field name="Value">JUMP_3X2</field>
      </fields>
      <pins>
        <pin num="1" name="2" type="passive"/>
        <pin num="2" name="2" type="passive"/>
        <pin num="3" name="4" type="passive"/>
        <pin num="4" name="4" type="passive"/>
        <pin num="5" name="6" type="passive"/>
        <pin num="6" name="6" type="passive"/>
      </pins>
    </libpart>
    <libpart lib="MLAB_MECHANICAL" part="HOLE">
      <fields>
        <field name="Reference">M</field>
        <field name="Value">HOLE</field>
      </fields>
      <pins>
        <pin num="1" name="" type="input"/>
      </pins>
    </libpart>
    <libpart lib="Memory_Flash" part="AT25SF081-SSHD-X">
      <description>8-Mbit, 2.5V Minimum SPI Serial Flash Memory with Dual-I/O and Quad-I/O Support, SOIC-8</description>
      <docs>https://www.adestotech.com/wp-content/uploads/DS-AT25SF081_045.pdf</docs>
      <footprints>
        <fp>SOIC?8*3.9x4.9mm*P1.27mm*</fp>
      </footprints>
      <fields>
        <field name="Reference">U</field>
        <field name="Value">AT25SF081-SSHD-X</field>
        <field name="Footprint">Package_SO:SOIC-8_3.9x4.9mm_P1.27mm</field>
        <field name="Datasheet">https://www.adestotech.com/wp-content/uploads/DS-AT25SF081_045.pdf</field>
      </fields>
      <pins>
        <pin num="1" name="~{CS}" type="input"/>
        <pin num="2" name="SO/IO1" type="bidirectional"/>
        <pin num="3" name="~{WP}/IO2" type="bidirectional"/>
        <pin num="4" name="GND" type="power_in"/>
        <pin num="5" name="SI/IO0" type="bidirectional"/>
        <pin num="6" name="SCK" type="input"/>
        <pin num="7" name="~{HOLD}/IO3" type="bidirectional"/>
        <pin num="8" name="VCC" type="power_in"/>
      </pins>
    </libpart>
    <libpart lib="Oscillator" part="XO91">
      <description>HCMOS Clock Oscillator</description>
      <docs>http://cdn-reichelt.de/documents/datenblatt/B400/XO91.pdf</docs>
      <footprints>
        <fp>Oscillator*SMD*EuroQuartz*XO91*7.0x5.0mm*</fp>
      </footprints>
      <fields>
        <field name="Reference">X</field>
        <field name="Value">XO91</field>
        <field name="Footprint">Oscillator:Oscillator_SMD_EuroQuartz_XO91-4Pin_7.0x5.0mm</field>
        <field name="Datasheet">http://cdn-reichelt.de/documents/datenblatt/B400/XO91.pdf</field>
      </fields>
      <pins>
        <pin num="1" name="EN" type="input"/>
        <pin num="2" name="GND" type="power_in"/>
        <pin num="3" name="OUT" type="output"/>
        <pin num="4" name="V+" type="power_in"/>
      </pins>
    </libpart>
    <libpart lib="Regulator_Linear" part="MIC5504-1.2YM5">
      <description>300mA Low-dropout Voltage Regulator, Vout 1.2V, Vin up to 5.5V, SOT-23</description>
      <docs>http://ww1.microchip.com/downloads/en/DeviceDoc/MIC550X.pdf</docs>
      <footprints>
        <fp>SOT?23?5*</fp>
      </footprints>
      <fields>
        <field name="Reference">U</field>
        <field name="Value">MIC5504-1.2YM5</field>
        <field name="Footprint">Package_TO_SOT_SMD:SOT-23-5</field>
        <field name="Datasheet">http://ww1.microchip.com/downloads/en/DeviceDoc/MIC550X.pdf</field>
      </fields>
      <pins>
        <pin num="1" name="VIN" type="power_in"/>
        <pin num="2" name="GND" type="power_in"/>
        <pin num="3" name="EN" type="input"/>
        <pin num="4" name="NC" type="no_connect"/>
        <pin num="5" name="VOUT" type="power_out"/>
      </pins>
    </libpart>
    <libpart lib="Switch" part="SW_Push">
      <description>Push button switch, generic, two pins</description>
      <docs>~</docs>
      <fields>
        <field name="Reference">SW</field>
        <field name="Value">SW_Push</field>
        <field name="Datasheet">~</field>
      </fields>
      <pins>
        <pin num="1" name="1" type="passive"/>
        <pin num="2" name="2" type="passive"/>
      </pins>
    </libpart>
  </libparts>
  <libraries>
    <library logical="Device">
      <uri>/usr/share/kicad/symbols//Device.kicad_sym</uri>
    </library>
    <library logical="FPGA_Lattice">
      <uri>/usr/share/kicad/symbols//FPGA_Lattice.kicad_sym</uri>
    </library>
    <library logical="Memory_Flash">
      <uri>/usr/share/kicad/symbols//Memory_Flash.kicad_sym</uri>
    </library>
    <library logical="Oscillator">
      <uri>/usr/share/kicad/symbols//Oscillator.kicad_sym</uri>
    </library>
    <library logical="Regulator_Linear">
      <uri>/usr/share/kicad/symbols//Regulator_Linear.kicad_sym</uri>
    </library>
    <library logical="Switch">
      <uri>/usr/share/kicad/symbols//Switch.kicad_sym</uri>
    </library>
  </libraries>
  <nets>
    <net code="1" name="+1V2">
      <node ref="C1" pin="2" pintype="passive"/>
      <node ref="C4" pin="1" pintype="passive"/>
      <node ref="R4" pin="2" pintype="passive"/>
      <node ref="U1" pin="3" pinfunction="ON" pintype="input"/>
      <node ref="U2" pin="5" pinfunction="VOUT" pintype="power_out"/>
      <node ref="U4" pin="30" pinfunction="VCC" pintype="passive"/>
      <node ref="U4" pin="5" pinfunction="VCC" pintype="power_in"/>
    </net>
    <net code="2" name="+3V3">
      <node ref="C2" pin="1" pintype="passive"/>
      <node ref="C7" pin="1" pintype="passive"/>
      <node ref="D1" pin="1" pinfunction="K" pintype="passive"/>
      <node ref="D2" pin="2" pinfunction="A" pintype="passive"/>
      <node ref="D3" pin="2" pinfunction="A" pintype="passive"/>
      <node ref="J1" pin="3" pinfunction="4" pintype="passive"/>
      <node ref="J1" pin="4" pinfunction="4" pintype="passive"/>
      <node ref="R1" pin="1" pintype="passive"/>
      <node ref="U1" pin="1" pinfunction="IN" pintype="power_in"/>
      <node ref="U2" pin="1" pinfunction="VIN" pintype="power_in"/>
      <node ref="U2" pin="3" pinfunction="EN" pintype="input"/>
      <node ref="U3" pin="3" pinfunction="~{WP}/IO2" pintype="bidirectional"/>
      <node ref="U3" pin="8" pinfunction="VCC" pintype="power_in"/>
      <node ref="X1" pin="1" pinfunction="EN" pintype="input"/>
      <node ref="X1" pin="4" pinfunction="V+" pintype="power_in"/>
    </net>
    <net code="3" name="/IOB_0a">
      <node ref="J27" pin="1" pintype="input"/>
      <node ref="J27" pin="2" pintype="input"/>
      <node ref="U4" pin="46" pinfunction="IOB_0a" pintype="bidirectional"/>
    </net>
    <net code="4" name="/IOB_2a">
      <node ref="J28" pin="1" pintype="input"/>
      <node ref="J28" pin="2" pintype="input"/>
      <node ref="U4" pin="47" pinfunction="IOB_2a" pintype="bidirectional"/>
    </net>
    <net code="5" name="/IOB_3b_G6">
      <node ref="J29" pin="1" pintype="input"/>
      <node ref="J29" pin="2" pintype="input"/>
      <node ref="U4" pin="44" pinfunction="IOB_3b_G6" pintype="bidirectional"/>
    </net>
    <net code="6" name="/IOB_4a">
      <node ref="J30" pin="1" pintype="input"/>
      <node ref="J30" pin="2" pintype="input"/>
      <node ref="U4" pin="48" pinfunction="IOB_4a" pintype="bidirectional"/>
    </net>
    <net code="7" name="/IOB_5b">
      <node ref="J31" pin="1" pintype="input"/>
      <node ref="J31" pin="2" pintype="input"/>
      <node ref="U4" pin="45" pinfunction="IOB_5b" pintype="bidirectional"/>
    </net>
    <net code="8" name="/IOB_6a">
      <node ref="J32" pin="1" pintype="input"/>
      <node ref="J32" pin="2" pintype="input"/>
      <node ref="U4" pin="2" pinfunction="IOB_6a" pintype="bidirectional"/>
    </net>
    <net code="9" name="/IOB_8a">
      <node ref="J33" pin="1" pintype="input"/>
      <node ref="J33" pin="2" pintype="input"/>
      <node ref="U4" pin="4" pinfunction="IOB_8a" pintype="bidirectional"/>
    </net>
    <net code="10" name="/IOB_9b">
      <node ref="J34" pin="1" pintype="input"/>
      <node ref="J34" pin="2" pintype="input"/>
      <node ref="U4" pin="3" pinfunction="IOB_9b" pintype="bidirectional"/>
    </net>
    <net code="11" name="/IOB_13b">
      <node ref="J5" pin="1" pintype="input"/>
      <node ref="J5" pin="2" pintype="input"/>
      <node ref="U4" pin="6" pinfunction="IOB_13b" pintype="bidirectional"/>
    </net>
    <net code="12" name="/IOB_16a">
      <node ref="J6" pin="1" pintype="input"/>
      <node ref="J6" pin="2" pintype="input"/>
      <node ref="U4" pin="9" pinfunction="IOB_16a" pintype="bidirectional"/>
    </net>
    <net code="13" name="/IOB_18a">
      <node ref="J7" pin="1" pintype="input"/>
      <node ref="J7" pin="2" pintype="input"/>
      <node ref="U4" pin="10" pinfunction="IOB_18a" pintype="bidirectional"/>
    </net>
    <net code="14" name="/IOB_20a">
      <node ref="J8" pin="1" pintype="input"/>
      <node ref="J8" pin="2" pintype="input"/>
      <node ref="U4" pin="11" pinfunction="IOB_20a" pintype="bidirectional"/>
    </net>
    <net code="15" name="/IOB_22b">
      <node ref="J9" pin="1" pintype="input"/>
      <node ref="J9" pin="2" pintype="input"/>
      <node ref="U4" pin="12" pinfunction="IOB_22b" pintype="bidirectional"/>
    </net>
    <net code="16" name="/IOB_23b">
      <node ref="J10" pin="1" pintype="input"/>
      <node ref="J10" pin="2" pintype="input"/>
      <node ref="U4" pin="21" pinfunction="IOB_23b" pintype="bidirectional"/>
    </net>
    <net code="17" name="/IOB_24a">
      <node ref="J11" pin="1" pintype="input"/>
      <node ref="J11" pin="2" pintype="input"/>
      <node ref="U4" pin="13" pinfunction="IOB_24a" pintype="bidirectional"/>
    </net>
    <net code="18" name="/IOB_25b">
      <node ref="U4" pin="20" pinfunction="IOB_25b_G3" pintype="bidirectional"/>
      <node ref="X1" pin="3" pinfunction="OUT" pintype="output"/>
    </net>
    <net code="19" name="/IOB_29b">
      <node ref="J13" pin="1" pintype="input"/>
      <node ref="J13" pin="2" pintype="input"/>
      <node ref="U4" pin="19" pinfunction="IOB_29b" pintype="bidirectional"/>
    </net>
    <net code="20" name="/IOB_31b">
      <node ref="J14" pin="1" pintype="input"/>
      <node ref="J14" pin="2" pintype="input"/>
      <node ref="U4" pin="18" pinfunction="IOB_31b" pintype="bidirectional"/>
    </net>
    <net code="21" name="/IOT_36b">
      <node ref="J26" pin="3" pinfunction="3" pintype="passive"/>
      <node ref="R7" pin="2" pintype="passive"/>
      <node ref="U4" pin="25" pinfunction="IOT_36b" pintype="bidirectional"/>
    </net>
    <net code="22" name="/IOT_37a">
      <node ref="J26" pin="2" pinfunction="2" pintype="passive"/>
      <node ref="R7" pin="1" pintype="passive"/>
      <node ref="U4" pin="23" pinfunction="IOT_37a" pintype="bidirectional"/>
    </net>
    <net code="23" name="/IOT_38b">
      <node ref="J26" pin="6" pinfunction="6" pintype="passive"/>
      <node ref="R8" pin="2" pintype="passive"/>
      <node ref="U4" pin="27" pinfunction="IOT_38b" pintype="bidirectional"/>
    </net>
    <net code="24" name="/IOT_39a">
      <node ref="J26" pin="5" pinfunction="5" pintype="passive"/>
      <node ref="R8" pin="1" pintype="passive"/>
      <node ref="U4" pin="26" pinfunction="IOT_39a" pintype="bidirectional"/>
    </net>
    <net code="25" name="/IOT_41a">
      <node ref="J15" pin="1" pintype="input"/>
      <node ref="J15" pin="2" pintype="input"/>
      <node ref="U4" pin="28" pinfunction="IOT_41a" pintype="bidirectional"/>
    </net>
    <net code="26" name="/IOT_42b">
      <node ref="J16" pin="1" pintype="input"/>
      <node ref="J16" pin="2" pintype="input"/>
      <node ref="U4" pin="31" pinfunction="IOT_42b" pintype="bidirectional"/>
    </net>
    <net code="27" name="/IOT_43a">
      <node ref="J17" pin="1" pintype="input"/>
      <node ref="J17" pin="2" pintype="input"/>
      <node ref="U4" pin="32" pinfunction="IOT_43a" pintype="bidirectional"/>
    </net>
    <net code="28" name="/IOT_44b">
      <node ref="J18" pin="1" pintype="input"/>
      <node ref="J18" pin="2" pintype="input"/>
      <node ref="U4" pin="34" pinfunction="IOT_44b" pintype="bidirectional"/>
    </net>
    <net code="29" name="/IOT_45a_G1">
      <node ref="J19" pin="1" pintype="input"/>
      <node ref="J19" pin="2" pintype="input"/>
      <node ref="U4" pin="37" pinfunction="IOT_45a_G1" pintype="bidirectional"/>
    </net>
    <net code="30" name="/IOT_46b_G0">
      <node ref="J20" pin="1" pintype="input"/>
      <node ref="J20" pin="2" pintype="input"/>
      <node ref="U4" pin="35" pinfunction="IOT_46b_G0" pintype="bidirectional"/>
    </net>
    <net code="31" name="/IOT_48b">
      <node ref="J21" pin="1" pintype="input"/>
      <node ref="J21" pin="2" pintype="input"/>
      <node ref="U4" pin="36" pinfunction="IOT_48b" pintype="bidirectional"/>
    </net>
    <net code="32" name="/IOT_49a">
      <node ref="J22" pin="1" pintype="input"/>
      <node ref="J22" pin="2" pintype="input"/>
      <node ref="U4" pin="43" pinfunction="IOT_49a" pintype="bidirectional"/>
    </net>
    <net code="33" name="/IOT_50b">
      <node ref="J23" pin="1" pintype="input"/>
      <node ref="J23" pin="2" pintype="input"/>
      <node ref="U4" pin="38" pinfunction="IOT_50b" pintype="bidirectional"/>
    </net>
    <net code="34" name="/IOT_51a">
      <node ref="J24" pin="1" pintype="input"/>
      <node ref="J24" pin="2" pintype="input"/>
      <node ref="U4" pin="42" pinfunction="IOT_51a" pintype="bidirectional"/>
    </net>
    <net code="35" name="/NRESET">
      <node ref="J4" pin="7" pintype="input"/>
      <node ref="R6" pin="2" pintype="passive"/>
      <node ref="SW1" pin="1" pinfunction="1" pintype="passive"/>
      <node ref="U4" pin="8" pinfunction="~{CRESET}" pintype="input"/>
    </net>
    <net code="36" name="/RGB0">
      <node ref="J25" pin="1" pintype="input"/>
      <node ref="J25" pin="2" pintype="input"/>
      <node ref="U4" pin="39" pinfunction="RGB0" pintype="open_collector"/>
    </net>
    <net code="37" name="/RGB1">
      <node ref="R9" pin="2" pintype="passive"/>
      <node ref="U4" pin="40" pinfunction="RGB1" pintype="open_collector"/>
    </net>
    <net code="38" name="/RGB2">
      <node ref="R10" pin="2" pintype="passive"/>
      <node ref="U4" pin="41" pinfunction="RGB2" pintype="open_collector"/>
    </net>
    <net code="39" name="/SPI_SCK">
      <node ref="J4" pin="5" pintype="input"/>
      <node ref="U3" pin="6" pinfunction="SCK" pintype="input"/>
      <node ref="U4" pin="15" pinfunction="IOB_34a_SPI_SCK" pintype="bidirectional"/>
    </net>
    <net code="40" name="/SPI_SI">
      <node ref="J4" pin="4" pintype="input"/>
      <node ref="U3" pin="5" pinfunction="SI/IO0" pintype="bidirectional"/>
      <node ref="U4" pin="14" pinfunction="IOB_32a_SPI_SO" pintype="bidirectional"/>
    </net>
    <net code="41" name="/SPI_SO">
      <node ref="J4" pin="6" pintype="input"/>
      <node ref="U3" pin="2" pinfunction="SO/IO1" pintype="bidirectional"/>
      <node ref="U4" pin="17" pinfunction="IOB_33b_SPI_SI" pintype="bidirectional"/>
    </net>
    <net code="42" name="/SPI_SS">
      <node ref="J4" pin="2" pintype="input"/>
      <node ref="R5" pin="2" pintype="passive"/>
      <node ref="U3" pin="1" pinfunction="~{CS}" pintype="input"/>
      <node ref="U4" pin="16" pinfunction="IOB_35b_SPI_SS" pintype="bidirectional"/>
    </net>
    <net code="43" name="/VCCIO_0">
      <node ref="C8" pin="1" pintype="passive"/>
      <node ref="J3" pin="1" pintype="input"/>
      <node ref="J3" pin="2" pintype="input"/>
      <node ref="R3" pin="2" pintype="passive"/>
      <node ref="U4" pin="33" pinfunction="VCCIO_0" pintype="power_in"/>
    </net>
    <net code="44" name="/VCCIO_1">
      <node ref="C9" pin="2" pintype="passive"/>
      <node ref="R2" pin="1" pintype="passive"/>
      <node ref="R3" pin="1" pintype="passive"/>
      <node ref="R5" pin="1" pintype="passive"/>
      <node ref="R6" pin="1" pintype="passive"/>
      <node ref="U1" pin="5" pinfunction="QOD" pintype="bidirectional"/>
      <node ref="U1" pin="6" pinfunction="OUT" pintype="power_out"/>
      <node ref="U4" pin="22" pinfunction="SPI_VCCIO1" pintype="power_in"/>
      <node ref="U4" pin="24" pinfunction="VPP_2V5" pintype="power_in"/>
    </net>
    <net code="45" name="/VCCIO_2">
      <node ref="C10" pin="2" pintype="passive"/>
      <node ref="J3" pin="3" pintype="input"/>
      <node ref="J3" pin="4" pintype="input"/>
      <node ref="R2" pin="2" pintype="passive"/>
      <node ref="U4" pin="1" pinfunction="VCCIO_2" pintype="power_in"/>
    </net>
    <net code="46" name="GND">
      <node ref="C1" pin="1" pintype="passive"/>
      <node ref="C10" pin="1" pintype="passive"/>
      <node ref="C2" pin="2" pintype="passive"/>
      <node ref="C4" pin="2" pintype="passive"/>
      <node ref="C5" pin="2" pintype="passive"/>
      <node ref="C6" pin="2" pintype="passive"/>
      <node ref="C7" pin="2" pintype="passive"/>
      <node ref="C8" pin="2" pintype="passive"/>
      <node ref="C9" pin="1" pintype="passive"/>
      <node ref="D1" pin="2" pinfunction="A" pintype="passive"/>
      <node ref="J1" pin="1" pinfunction="2" pintype="passive"/>
      <node ref="J1" pin="2" pinfunction="2" pintype="passive"/>
      <node ref="J1" pin="5" pinfunction="6" pintype="passive"/>
      <node ref="J1" pin="6" pinfunction="6" pintype="passive"/>
      <node ref="J2" pin="2" pintype="input"/>
      <node ref="J26" pin="1" pinfunction="1" pintype="passive"/>
      <node ref="J26" pin="4" pinfunction="4" pintype="passive"/>
      <node ref="J26" pin="7" pinfunction="7" pintype="passive"/>
      <node ref="J4" pin="1" pintype="input"/>
      <node ref="J4" pin="3" pintype="input"/>
      <node ref="J4" pin="8" pintype="input"/>
      <node ref="M1" pin="1" pintype="input"/>
      <node ref="M2" pin="1" pintype="input"/>
      <node ref="M3" pin="1" pintype="input"/>
      <node ref="M4" pin="1" pintype="input"/>
      <node ref="SW1" pin="2" pinfunction="2" pintype="passive"/>
      <node ref="U1" pin="2" pinfunction="GND" pintype="input"/>
      <node ref="U2" pin="2" pinfunction="GND" pintype="power_in"/>
      <node ref="U3" pin="4" pinfunction="GND" pintype="power_in"/>
      <node ref="U4" pin="49" pinfunction="GND" pintype="power_in"/>
      <node ref="X1" pin="2" pinfunction="GND" pintype="power_in"/>
    </net>
    <net code="47" name="Net-(C5-Pad1)">
      <node ref="C5" pin="1" pintype="passive"/>
      <node ref="C6" pin="1" pintype="passive"/>
      <node ref="R4" pin="1" pintype="passive"/>
      <node ref="U4" pin="29" pinfunction="VCCPLL" pintype="power_out"/>
    </net>
    <net code="48" name="Net-(D2-Pad1)">
      <node ref="D2" pin="1" pinfunction="K" pintype="passive"/>
      <node ref="R9" pin="1" pintype="passive"/>
    </net>
    <net code="49" name="Net-(D3-Pad1)">
      <node ref="D3" pin="1" pinfunction="K" pintype="passive"/>
      <node ref="R10" pin="1" pintype="passive"/>
    </net>
    <net code="50" name="Net-(J2-Pad1)">
      <node ref="J2" pin="1" pintype="input"/>
      <node ref="R1" pin="2" pintype="passive"/>
      <node ref="U3" pin="7" pinfunction="~{HOLD}/IO3" pintype="bidirectional"/>
    </net>
    <net code="51" name="unconnected-(C3-Pad1)">
      <node ref="C3" pin="1" pintype="passive"/>
    </net>
    <net code="52" name="unconnected-(C3-Pad2)">
      <node ref="C3" pin="2" pintype="passive"/>
    </net>
    <net code="53" name="unconnected-(U2-Pad4)">
      <node ref="U2" pin="4" pinfunction="NC" pintype="no_connect"/>
    </net>
    <net code="54" name="unconnected-(U4-Pad7)">
      <node ref="U4" pin="7" pinfunction="CDONE" pintype="open_collector+no_connect"/>
    </net>
  </nets>
</export>
